argilla_plugins/__init__.py
argilla_plugins/__main__.py
argilla_plugins/_plugin_template.py
argilla_plugins/active_learning/__init__.py
argilla_plugins/active_learning/classy_learner.py
argilla_plugins/datasets/__init__.py
argilla_plugins/datasets/end_of_life.py
argilla_plugins/inference/__init__.py
argilla_plugins/inference/embedder.py
argilla_plugins/programmatic_labelling/__init__.py
argilla_plugins/programmatic_labelling/token_copycat.py
argilla_plugins/reporting/__init__.py
argilla_plugins/utils/cli_tools.py
argilla_plugins/utils/dependency_checker.py
argilla_plugins-0.1.3.dist-info/LICENSE
argilla_plugins-0.1.3.dist-info/WHEEL
argilla_plugins-0.1.3.dist-info/METADATA
argilla_plugins-0.1.3.dist-info/RECORD
