Metadata-Version: 2.1
Name: argilla-plugins
Version: 0.1.3
Summary: 🔌 Open-source plugins for with practical features for Argilla using listeners.
License: Apache 2.0
Author: david
Author-email: david.m.berenstein@gmail.com
Requires-Python: >=3.8,<3.11.0
Classifier: License :: Other/Proprietary License
Classifier: Programming Language :: Python :: 3
Classifier: Programming Language :: Python :: 3.8
Classifier: Programming Language :: Python :: 3.9
Classifier: Programming Language :: Python :: 3.10
Provides-Extra: reporting-datapane
Provides-Extra: reporting-greatexpectations
Requires-Dist: argilla[listeners] (>=1.3.0,<2.0.0)
Requires-Dist: asyncio (>=3.4.3,<4.0.0)
Requires-Dist: classy-classification (>=0.6.2,<0.7.0)
Requires-Dist: datapane (>=0.15.5,<0.16.0); extra == "reporting-datapane"
Requires-Dist: great-expectations (>=0.15,<0.16); extra == "reporting-greatexpectations"
Requires-Dist: rich[jupyter] (>=13.0.0,<14.0.0)
Requires-Dist: typer (>=0.7.0,<0.8.0)
